toc_markdown/__init__.py
toc_markdown/cli.py
toc_markdown-0.0.2.dist-info/LICENSE
toc_markdown-0.0.2.dist-info/METADATA
toc_markdown-0.0.2.dist-info/WHEEL
toc_markdown-0.0.2.dist-info/entry_points.txt
toc_markdown-0.0.2.dist-info/top_level.txt
toc_markdown-0.0.2.dist-info/RECORD
