Metadata-Version: 2.1
Name: toc-markdown
Version: 0.0.2
Summary: Generate a table of contents for a Markdown file.
Home-page: https://github.com/sderev/toc-markdown
Author: Sébastien De Revière
License: Apache Licence, Version 2.0
Project-URL: Documentation, https://github.com/sderev/toc-markdown
Project-URL: Issues, http://github.com/sderev/toc-markdown/issues
Project-URL: Changelog, https://github.com/sderev/toc-markdown/releases
Requires-Python: >=3.8
License-File: LICENSE
Requires-Dist: click
